README.rst
setup.cfg
setup.py
pyxdeco/__init__.py
pyxdeco/_decorators.py
pyxdeco/advice.py
pyxdeco/tests.py
pyxdeco.egg-info/PKG-INFO
pyxdeco.egg-info/SOURCES.txt
pyxdeco.egg-info/dependency_links.txt
pyxdeco.egg-info/entry_points.txt
pyxdeco.egg-info/top_level.txt
pyxdeco.egg-info/zip-safe