Metadata-Version: 1.0
Name: pyxdeco
Version: 0.1.2
Summary: Python eXtraordinary Decorators
Home-page: http://github.com/iancmcc/pyxdeco
Author: Ian McCracken
Author-email: ian.mccracken@gmail.com
License: MIT
Platform: UNKNOWN
